langchain_fastapi_chat_completion/__init__.py
langchain_fastapi_chat_completion/chat_completion/chat_completion_chunk_choice_adapter.py
langchain_fastapi_chat_completion/chat_completion/chat_completion_chunk_object_factory.py
langchain_fastapi_chat_completion/chat_completion/chat_completion_compatible_api.py
langchain_fastapi_chat_completion/chat_completion/chat_completion_object_factory.py
langchain_fastapi_chat_completion/chat_completion/content_adapter.py
langchain_fastapi_chat_completion/chat_completion/http_stream_response_adapter.py
langchain_fastapi_chat_completion/chat_completion/langchain_invoke_adapter.py
langchain_fastapi_chat_completion/chat_completion/langchain_stream_adapter.py
langchain_fastapi_chat_completion/chat_model_adapter/__init__.py
langchain_fastapi_chat_completion/chat_model_adapter/anthropic/__init__.py
langchain_fastapi_chat_completion/chat_model_adapter/anthropic/anthropic_openai_compatible_chat_model.py
langchain_fastapi_chat_completion/chat_model_adapter/anthropic/anthropic_openai_compatible_chat_model_adapter.py
langchain_fastapi_chat_completion/chat_model_adapter/base_openai_compatible_chat_model_adapter.py
langchain_fastapi_chat_completion/chat_model_adapter/llamacpp/__init__.py
langchain_fastapi_chat_completion/chat_model_adapter/llamacpp/llamacpp_openai_compatible_chat_model.py
langchain_fastapi_chat_completion/chat_model_adapter/llamacpp/llamacpp_openai_compatible_chat_model_adapter.py
langchain_fastapi_chat_completion/chat_model_adapter/url_extractor.py
langchain_fastapi_chat_completion/core/__init__.py
langchain_fastapi_chat_completion/core/base_agent_factory.py
langchain_fastapi_chat_completion/core/create_agent_dto.py
langchain_fastapi_chat_completion/core/function_agent_factory.py
langchain_fastapi_chat_completion/core/langchain_openai_api_bridge.py
langchain_fastapi_chat_completion/core/role_adapter.py
langchain_fastapi_chat_completion/core/types/openai/__init__.py
langchain_fastapi_chat_completion-1.0.9.dist-info/METADATA
langchain_fastapi_chat_completion-1.0.9.dist-info/WHEEL
langchain_fastapi_chat_completion-1.0.9.dist-info/entry_points.txt
langchain_fastapi_chat_completion-1.0.9.dist-info/licenses/LICENSE
langchain_fastapi_chat_completion-1.0.9.dist-info/RECORD
