Metadata-Version: 2.4
Name: langchain-fastapi-chat-completion
Version: 1.0.9
Summary: A bridge to use Langchain output as an OpenAI chat completion API.
License: MIT
License-File: LICENSE
Author: Kim Minjong
Author-email: make.dirty.code@gmail.com
Requires-Python: >=3.11,<4.0
Classifier: License :: OSI Approved :: MIT License
Classifier: Programming Language :: Python :: 3
Classifier: Programming Language :: Python :: 3.11
Classifier: Programming Language :: Python :: 3.12
Classifier: Programming Language :: Python :: 3.13
Classifier: Programming Language :: Python :: 3.14
Provides-Extra: anthropic
Provides-Extra: groq
Provides-Extra: langchain
Provides-Extra: langchain-serve
Requires-Dist: fastapi[standard] (>=0.115.14,<0.116.0) ; extra == "langchain-serve"
Requires-Dist: langchain (>=0.3.26,<0.4.0) ; extra == "langchain"
Requires-Dist: langchain-anthropic (>=0.3.16,<0.4.0) ; extra == "anthropic"
Requires-Dist: langchain-groq (>=0.3.4,<0.4.0) ; extra == "groq"
Requires-Dist: langchain-openai (>=0.3.27,<0.4.0) ; extra == "langchain"
Requires-Dist: langgraph (>=0.5.0,<0.6.0) ; extra == "langchain"
Requires-Dist: openai (>=1.93.0,<2.0.0)
Requires-Dist: pydantic (>=2.8.0,<2.9.0)
Requires-Dist: python-dotenv (>=1.0.1,<2.0.0) ; extra == "langchain-serve"
Project-URL: Repository, https://github.com/caffeinism/langchain-fastapi-chat-completion
